{
    "criteria": {
        "nether_star": {
            "trigger": "inventory_changed",
            "conditions": {
                "items": [
                    {
                        "items": "nether_star",
                        "components": {
                            "item_name": {
                                "translate": "item.minecraft.nether_star"
                            }
                        },
                        "count": {
                            "min": 1,
                            "max": 64
                        }
                    }
                ]
            }
        }
    },
    "rewards": {
        "function": "yw-pillar:utils/game/item/nether_star/give"
    }
}